{
    "VAL_WEIGHT_PATH": "<path_to>/fcn8_COMBINED_19_10_10_173426/08.h5",
    "BATCH_SIZE": 8,
    "DISPLAY_SCALE_FACTOR": 1.25,
    "MODEL": "fcn8",
    "MODE": "VALIDATE",
    "PRE_PROCESS": {
        "edge": [
            0,
            3
        ],
        "grey": [
            117
        ],
        "rgb": [
            182.11864,
            155.26283,
            107.5
        ],
        "ycr": [
            123,
            126,
            120
        ],
        "lab": [
            50,
            0.1,
            1.5
        ]
    },
    "CHANNEL": "STACKED",
    "CLASS_NAMES": [
        "weld"
    ],
    "ORIG_DIMS": [
        480,
        640
    ],
    "CONFIDENCE_THRESHOLD": 0.5
}